cowincli/__init__.py
cowincli/main.py
cowincli-0.0.1.dist-info/LICENSE
cowincli-0.0.1.dist-info/METADATA
cowincli-0.0.1.dist-info/WHEEL
cowincli-0.0.1.dist-info/top_level.txt
cowincli-0.0.1.dist-info/RECORD
